arcticfreeze/__init__.py
arcticfreeze/__main__.py
arcticfreeze/_internal/__init__.py
arcticfreeze/_internal/freeze.py
arcticfreeze/_internal/frozendict.py
arcticfreeze/_internal/resolve.py
arcticfreeze/_internal/utils.py
arcticfreeze/_internal/_converters/__init__.py
arcticfreeze/_internal/_converters/base.py
arcticfreeze/_internal/_converters/standard.py
arcticfreeze-0.1.1.dist-info/LICENSE
arcticfreeze-0.1.1.dist-info/METADATA
arcticfreeze-0.1.1.dist-info/WHEEL
arcticfreeze-0.1.1.dist-info/top_level.txt
arcticfreeze-0.1.1.dist-info/RECORD
