Metadata-Version: 2.1
Name: arcticfreeze
Version: 0.1.1
Summary: Enjoy Python on the rocks with deeply (recursively) frozen data structures.
Author-email: KerstenBreuer <kersten-breuer@outlook.com>
License: Apache 2.0
Project-URL: Repository, https://github.com/kerstenbreuer/arcticfreeze
Classifier: Development Status :: 1 - Planning
Classifier: Programming Language :: Python :: 3.9
Classifier: Programming Language :: Python :: 3.10
Classifier: Programming Language :: Python :: 3.11
Classifier: Programming Language :: Python :: 3.12
Classifier: License :: OSI Approved :: Apache Software License
Classifier: Topic :: Software Development :: Libraries
Classifier: Intended Audience :: Developers
Requires-Python: >=3.9
License-File: LICENSE
Requires-Dist: immutabledict <5,>=4
Provides-Extra: pydantic
Requires-Dist: pydantic <3,>=2 ; extra == 'pydantic'
